{
	"info": {
		"_postman_id": "c9023011-1a13-44fd-b45e-648e380cdfc1",
		"name": "Himanshu-Project-Postman-Collection",
		"schema": "https://schema.getpostman.com/json/collection/v2.1.0/collection.json"
	},
	"item": [
		{
			"name": "GET All Employees",
			"event": [
				{
					"listen": "test",
					"script": {
						"id": "6f634420-5d60-4052-bcb1-95ca7d0448ca",
						"exec": [
							"pm.test(\"Status code is 200\", function () {\r",
							"    pm.response.to.have.status(200);\r",
							"});"
						],
						"type": "text/javascript"
					}
				}
			],
			"request": {
				"method": "GET",
				"header": [],
				"url": {
					"raw": "http://dummy.restapiexample.com/api/v1/employees",
					"protocol": "http",
					"host": [
						"dummy",
						"restapiexample",
						"com"
					],
					"path": [
						"api",
						"v1",
						"employees"
					]
				}
			},
			"response": []
		},
		{
			"name": "POST All Employees",
			"event": [
				{
					"listen": "test",
					"script": {
						"id": "17d86664-9236-4ec6-b6a0-1d1a06b4cbc0",
						"exec": [
							"pm.test(\"Status code is 200\", function () {\r",
							"    pm.response.to.have.status(200);\r",
							"});"
						],
						"type": "text/javascript"
					}
				}
			],
			"request": {
				"method": "POST",
				"header": [],
				"body": {
					"mode": "raw",
					"raw": "{\r\n    \"name\": \"test_gk_unique\",\r\n    \"salary\": \"123\",\r\n    \"age\": \"23\"\r\n}",
					"options": {
						"raw": {
							"language": "json"
						}
					}
				},
				"url": {
					"raw": "http://dummy.restapiexample.com/api/v1/create",
					"protocol": "http",
					"host": [
						"dummy",
						"restapiexample",
						"com"
					],
					"path": [
						"api",
						"v1",
						"create"
					]
				}
			},
			"response": []
		},
		{
			"name": "GET Employee 2982",
			"event": [
				{
					"listen": "test",
					"script": {
						"id": "d5fb70a5-0695-4325-8133-701b63b63141",
						"exec": [
							"pm.test(\"Status code is 200\", function () {\r",
							"    pm.response.to.have.status(200);\r",
							"});"
						],
						"type": "text/javascript"
					}
				}
			],
			"request": {
				"method": "GET",
				"header": [],
				"url": {
					"raw": "http://dummy.restapiexample.com/api/v1/employee/2982",
					"protocol": "http",
					"host": [
						"dummy",
						"restapiexample",
						"com"
					],
					"path": [
						"api",
						"v1",
						"employee",
						"2982"
					]
				}
			},
			"response": []
		},
		{
			"name": "PUT Employee 2982",
			"event": [
				{
					"listen": "test",
					"script": {
						"id": "e983fb6d-b3e4-4038-9aa3-b27bd8e9dcd4",
						"exec": [
							"pm.test(\"Status code is 200\", function () {\r",
							"    pm.response.to.have.status(200);\r",
							"});"
						],
						"type": "text/javascript"
					}
				}
			],
			"request": {
				"method": "PUT",
				"header": [],
				"url": {
					"raw": "http://dummy.restapiexample.com/api/v1/update/2982",
					"protocol": "http",
					"host": [
						"dummy",
						"restapiexample",
						"com"
					],
					"path": [
						"api",
						"v1",
						"update",
						"2982"
					]
				}
			},
			"response": []
		},
		{
			"name": "DELETE Employee 2982",
			"event": [
				{
					"listen": "test",
					"script": {
						"id": "d36dfe0c-7183-43df-9392-32774dcf835f",
						"exec": [
							"pm.test(\"Status code is 200\", function () {\r",
							"    pm.response.to.have.status(200);\r",
							"});"
						],
						"type": "text/javascript"
					}
				}
			],
			"request": {
				"method": "DELETE",
				"header": [],
				"url": {
					"raw": "http://dummy.restapiexample.com/api/v1/delete/2982",
					"protocol": "http",
					"host": [
						"dummy",
						"restapiexample",
						"com"
					],
					"path": [
						"api",
						"v1",
						"delete",
						"2982"
					]
				}
			},
			"response": []
		}
	],
	"protocolProfileBehavior": {}
}